{"cameraMode":{"drawMode":0,"name":"Shaded","section":"Shading Mode"},"sceneLighting":true,"audioPlay":false,"sceneViewState":{"showFog":true,"showMaterialUpdate":false,"showSkybox":true,"showFlares":true,"showImageEffects":true,"showParticleSystems":true},"in2DMode":false,"pivot":{"x":-12.30101203918457,"y":-1.80478835105896,"z":5.967419624328613},"rotation":{"x":0.13237114250659944,"y":0.84975665807724,"z":-0.25492024421691897,"w":0.442311555147171},"size":5.053046226501465,"orthographic":false}